{
  "sitemetadata": {
    "title": "دولوريس v2",
    "description": "التعلم من الماضي، وبناء المستقبل"
  },
  "homepage": {
    "title": "مرحبا بكم في دولوريس v2",
    "description": "استكشف جميع الميزات والتحسينات الجديدة في دولوريس v2.",
    "cta": "استكشاف كافة المشاريع"
  },
  "tldr": {
    "title": "ليرة تركية؛ د",
    "description": "شرح المواضيع المعقدة بعبارات بسيطة. احصل على ملخصات سريعة لمواضيع مختلفة."
  },
  "dolores": "دولوريس",
  "navbar": {
    "tldr": "ليرة تركية؛ د",
    "home": "بيت"
  },
  "pagination": {
    "next": "التالي",
    "previous": "سابق"
  },
  "browse_in_other_languages": "تصفح بلغات أخرى"
}
